pgbook/__init__.py
pgbook/eventlist/__init__.py
pgbook/eventlist/signal.py
pgbook/eventlist/thinglist.py
pgbook/object/__init__.py
pgbook/object/button.py
pgbook/object/object.py
pgbook/object/slidingbar.py
pgbook/object/text.py
pgbook/screen/__init__.py
pgbook/screen/page.py
pgbook/screen/window.py
pgbook/static/fonts/NotoFont.ttf
pgbook/static/pic/load.ico
pgbook-0.2.4.dist-info/METADATA
pgbook-0.2.4.dist-info/WHEEL
pgbook-0.2.4.dist-info/RECORD
