Metadata-Version: 2.1
Name: pgbook
Version: 0.2.4
Summary: Pygame Function Book
License: Apache License
Author: zaiecunmin
Author-email: zaiecunmin@qq.com
Requires-Python: >=3.8,<4.0
Classifier: License :: Other/Proprietary License
Classifier: Programming Language :: Python :: 3
Classifier: Programming Language :: Python :: 3.8
Classifier: Programming Language :: Python :: 3.9
Classifier: Programming Language :: Python :: 3.10
Classifier: Programming Language :: Python :: 3.11
Classifier: Programming Language :: Python :: 3.12
Requires-Dist: pygame (>=2.6.0,<3.0.0)
